

{
    "$schema": "https://schema.management.azure.com/schemas/2015-01-01/deploymentParameters.json#",
    "contentVersion": "1.0.0.0",
    "parameters": {
        "connections_sharepointonline_name": {
            "value": "sharepoint"
        },
        "location": {
            "value": "eastus"
        },
        "displayName": {
            "value": "Prod-Rss"
        },
        "sub-id": {
            "value": "beb2107a-2219-488b-929e-7939bb20b9a2"
        },
        "rg": {
            "value": "RG-Dev"
        }
    }
}



